advanced_dtypes/__init__.py
advanced_dtypes/const_store.py
advanced_dtypes/constants.py
advanced_dtypes/enum.py
advanced_dtypes-0.0.2.dist-info/LICENSE
advanced_dtypes-0.0.2.dist-info/METADATA
advanced_dtypes-0.0.2.dist-info/WHEEL
advanced_dtypes-0.0.2.dist-info/top_level.txt
advanced_dtypes-0.0.2.dist-info/RECORD
