Metadata-Version: 2.1
Name: advanced-dtypes
Version: 0.0.2
Summary: Data types not found in the standard library that are cool in various different ways ;)
Home-page: UNKNOWN
Author: Ben Lee
License: UNKNOWN
Project-URL: Source, https://github.com/benlee1284/advanced-dtypes
Project-URL: Tracker, https://github.com/benlee1284/advanced-dtypes/issues
Platform: UNKNOWN
Classifier: Programming Language :: Python :: 3
Classifier: License :: OSI Approved :: MIT License
Classifier: Operating System :: OS Independent
Requires-Python: >=3.6
License-File: LICENSE
